Nextcode-0.0.1.data/scripts/__init__.py
Nextcode-0.0.1.dist-info/DESCRIPTION.rst
Nextcode-0.0.1.dist-info/METADATA
Nextcode-0.0.1.dist-info/RECORD
Nextcode-0.0.1.dist-info/WHEEL
Nextcode-0.0.1.dist-info/entry_points.txt
Nextcode-0.0.1.dist-info/metadata.json
Nextcode-0.0.1.dist-info/top_level.txt
nextcode/__init__.py
