Metadata-Version: 2.0
Name: Nextcode
Version: 0.0.1
Summary: Nextcode sample processing tool
Home-page: https://www.wuxinextcode.com
Author: WUXI NextCODE
Author-email: jonb@wuxinextcode.com
License: UNKNOWN
Platform: UNKNOWN
Requires-Dist: requests
